README
setup.py
src/twisted_json_socket.egg-info/PKG-INFO
src/twisted_json_socket.egg-info/SOURCES.txt
src/twisted_json_socket.egg-info/dependency_links.txt
src/twisted_json_socket.egg-info/requires.txt
src/twisted_json_socket.egg-info/top_level.txt
src/twistedjsonsocket/__init__.py