Metadata-Version: 1.0
Name: twisted-json-socket
Version: 0.1.3
Summary: Protocol for twisted json socket
Home-page: https://bitbucket.org/madssj/twisted-json-socket
Author: Bo Kanstrup, Mads Sülau Jørgensen
Author-email: bkh@konstellation.dk, msj@konstellation.dk
License: BSD
Keywords: twsited json socket protocol
Platform: UNKNOWN
